pyelant/__init__.py
pyelant/__main__.py
pyelant/pyelant.py
pyelant-0.1.dist-info/LICENSE.txt
pyelant-0.1.dist-info/METADATA
pyelant-0.1.dist-info/WHEEL
pyelant-0.1.dist-info/top_level.txt
pyelant-0.1.dist-info/RECORD
