Metadata-Version: 2.1
Name: pyelant
Version: 0.1
Summary: Python tool for easily performing translations and storing it on the clipboard.
Home-page: https://github.com/paulomarcos/pyelant/
Author: Paulo Marcos
Author-email: paulomarcos@me.com
License: MIT
Download-URL: https://github.com/paulomarcos/pyelant/archive/v_01.tar.gz
Keywords: translation,clipboard,easy
Platform: UNKNOWN
Requires-Dist: googletrans (==3.1.0a0)
Requires-Dist: notify2 (==0.3.1)
Requires-Dist: pyaudio (==0.2.11)
Requires-Dist: pyperclip (==1.8.2)
Requires-Dist: pynput (==1.7.3)
Requires-Dist: SpeechRecognition (==3.8.1)
